cursingspock.py
setup.py
CursingSpock.egg-info/PKG-INFO
CursingSpock.egg-info/SOURCES.txt
CursingSpock.egg-info/dependency_links.txt
CursingSpock.egg-info/top_level.txt