Metadata-Version: 1.1
Name: CursingSpock
Version: 0.1.0
Summary: A SpockBot plugin for controlling the client from the terminal. Built with Curses.
Home-page: https://github.com/Gjum/CursingSpock
Author: Gjum
Author-email: code.gjum@gmail.com
License: MIT
Platform: UNKNOWN
Classifier: Development Status :: 4 - Beta
Classifier: Environment :: Console :: Curses
Classifier: Intended Audience :: Developers
Classifier: Intended Audience :: System Administrators
Classifier: License :: OSI Approved :: MIT License
Classifier: Natural Language :: English
Classifier: Programming Language :: Python :: 3.3
Classifier: Programming Language :: Python :: 3.4
Classifier: Programming Language :: Python :: 3.5
Classifier: Topic :: Games/Entertainment
Classifier: Topic :: Home Automation
Classifier: Topic :: System :: Monitoring
